postgresql_manager/__init__.py
postgresql_manager/columns.py
postgresql_manager/databases.py
postgresql_manager/manager.py
postgresql_manager/rows.py
postgresql_manager/tables.py
postgresql_manager-2.0.1.dist-info/METADATA
postgresql_manager-2.0.1.dist-info/WHEEL
postgresql_manager-2.0.1.dist-info/top_level.txt
postgresql_manager-2.0.1.dist-info/RECORD
