Metadata-Version: 2.4
Name: postgresql_manager
Version: 2.0.1
Summary: A simple PostgreSQL management package for handling databases, tables, columns, and rows.
Home-page: https://github.com/ximilsoft/postgresql_manager
Author: Xandor Telvanyx
Author-email: xandortelvanyx@ximilsoft.com
Classifier: Programming Language :: Python :: 3
Classifier: License :: OSI Approved :: MIT License
Classifier: Operating System :: OS Independent
Requires-Python: >=3.6
Requires-Dist: psycopg2
Dynamic: author
Dynamic: author-email
Dynamic: classifier
Dynamic: description
Dynamic: description-content-type
Dynamic: home-page
Dynamic: requires-dist
Dynamic: requires-python
Dynamic: summary
